LICENSE
README.md
setup.py
src/virtual_memory_toolkit/__init__.py
src/virtual_memory_toolkit/handles/__init__.py
src/virtual_memory_toolkit/handles/handle.h
src/virtual_memory_toolkit/handles/handle.pxd
src/virtual_memory_toolkit/memory/__init__.py
src/virtual_memory_toolkit/memory/memory_manager.h
src/virtual_memory_toolkit/memory/memory_manager.pxd
src/virtual_memory_toolkit/memory/memory_structures.h
src/virtual_memory_toolkit/memory/memory_structures.pxd
src/virtual_memory_toolkit/process/__init__.py
src/virtual_memory_toolkit/process/process.h
src/virtual_memory_toolkit/process/process.pxd
src/virtual_memory_toolkit/windows/__init__.py
src/virtual_memory_toolkit/windows/windows_defs.h
src/virtual_memory_toolkit/windows/windows_defs.pxd
src/virtual_memory_toolkit/windows/windows_types.h
src/virtual_memory_toolkit/windows/windows_types.pxd
virtual_memory_toolkit.egg-info/PKG-INFO
virtual_memory_toolkit.egg-info/SOURCES.txt
virtual_memory_toolkit.egg-info/dependency_links.txt
virtual_memory_toolkit.egg-info/top_level.txt