Metadata-Version: 2.1
Name: virtual-memory-toolkit
Version: 1.0.0
Summary: Virtual memory manipulation using Cython.
License-File: LICENSE
